mneGUI/__init__.py
mneGUI/__main__.py
mneGUI/bad_chs.py
mneGUI/baseline.py
mneGUI/check_channel_types.py
mneGUI/epochs.py
mneGUI/filter.py
mneGUI/ica.py
mneGUI/load_data.py
mneGUI/main_window.py
mneGUI/msgbxs.py
mneGUI/notch.py
mneGUI/pipeline_dicts.py
mneGUI/plot.py
mneGUI/plot_func_dialog_classes.py
mneGUI/prep_func_dialog_classes.py
mneGUI/reference.py
mneGUI/resample.py
mneGUI/save_data.py
mneUItest-0.0.18.dist-info/LICENSE.txt
mneUItest-0.0.18.dist-info/METADATA
mneUItest-0.0.18.dist-info/WHEEL
mneUItest-0.0.18.dist-info/top_level.txt
mneUItest-0.0.18.dist-info/RECORD
